miao.py
miao_make-20230627.dist-info/METADATA
miao_make-20230627.dist-info/WHEEL
miao_make-20230627.dist-info/entry_points.txt
miao_make-20230627.dist-info/top_level.txt
miao_make-20230627.dist-info/RECORD
