Metadata-Version: 2.1
Name: miao-make
Version: 20230627
Summary: Cargo-like project management tool for working with CMake
Author-email: Anji Wong <anzhi0708@gmail.com>
Project-URL: Homepage, https://github.com/anzhi0708/miao
Keywords: cmake,cmakelists
Classifier: Programming Language :: Python :: 3
Classifier: License :: OSI Approved :: MIT License
Classifier: Operating System :: OS Independent
Requires-Dist: colorama
Requires-Dist: fire
Requires-Dist: Jinja2
